Metadata-Version: 2.1
Name: example-python-package-mate
Version: 0.0.3
Summary: magic happens here
Home-page: https://github.com/mateczentye/example_python_package_mate
Author: Mate
Author-email: czentyemate@gmail.com
License: MIT
Platform: UNKNOWN
